[
    {
      "userId": 1,
      "id": 1,
      "title": "Imagem 1",
      "body": "Então siga sendo tudo que\nassusta alguns e encanta outros"
    },
    {
      "userId": 1,
      "id": 2,
      "title": "Imagem 2",
      "body": "Nasci pra viver a história\nmais importante de todas - a minha"
    },
    {
      "userId": 1,
      "id": 3,
      "title": "Imagem 3",
      "body": "Ela é firme, decidida,\njusta, doce, livre"
    },
    {
      "userId": 1,
      "id": 4,
      "title": "Imagem 4",
      "body": "Abençoada, protegida, iluminada, feliz,\ngrata pela vida e guiada por Deus"
    },
    {
      "userId": 1,
      "id": 5,
      "title": "Imagem 5",
      "body": "Aceite-se e perdoe-se. Rodeie-se de\namor e verdade. E siga sendo luz "
    },
    {
      "userId": 1,
      "id": 6,
      "title": "Imagem 6",
      "body": "Sempre procurando ser\na melhor versão de mim..."
    },
    {
      "userId": 1,
      "id": 7,
      "title": "Imagem 7",
      "body": "Seja mais você e menos o que\nos outros querem que você seja"
    },
    {
      "userId": 1,
      "id": 8,
      "title": "Imagem 8",
      "body": "Nenhuma beleza brilha mais\nque um bom coração. "    
    },
    {
      "userId": 1,
      "id": 9,
      "title": "Imagem 9",
      "body": "Que a vida seja vivida\nde gratidão em gratidão"    
    },
    {
      "userId": 1,
      "id": 10,
      "title": "Imagem 10",
      "body": "Me pertencer,\njá me basta"    
    },
    {
      "userId": 2,
      "id": 11,
      "title": "Imagem 11",
      "body": "Cada sorriso dela,\ntem muito de Deus!"    
    },
    {
      "userId": 2,
      "id": 12,
      "title": "Imagem 12",
      "body": "O tempo faz e traz\ncoisas incríveis!"    
    },
    {
      "userId": 2,
      "id": 13,
      "title": "Imagem 13",
      "body": "Evolua tanto que os outros\nprecisarão te conhecer de novo"    
    },
    {
      "userId": 2,
      "id": 14,
      "title": "Imagem 14",
      "body": "Eu sou bem melhor\nsozinha sabe... "    
    },
    {
      "userId": 2,
      "id": 15,
      "title": "Imagem 15",
      "body": "A minha fé é infinita, me\nacompanha por onde eu for"    
    },
    {
      "userId": 2,
      "id": 16,
      "title": "Imagem 16",
      "body": "Respire: a vida pede\nresiliência para cicatrizar"    
    },
    {
      "userId": 2,
      "id": 17,
      "title": "Imagem 17",
      "body": "Olhe dentro dos meus\nolhos, decifra-me"    
    },
    {
      "userId": 2,
      "id": 18,
      "title": "Imagem 18",
      "body": "Por me conhecer, posso viver.\nPor viver, posso me olhar.\nPor me ver por inteiro, posso ser feliz.\nPor ser feliz, posso agradecer!"    
    },
    {
      "userId": 2,
      "id": 19,
      "title": "Imagem 19",
      "body": "Só existe vida. E tudo\nque cabe nela, já é."    
    },
    {
      "userId": 2,
      "id": 20,
      "title": "Imagem 20",
      "body": "Cada dia mais minha,\nmenos deles, menos sua."    
    },
    {
      "userId": 3,
      "id": 21,
      "title": "Imagem 21",
      "body": "Aceite o que é, deixe ir o que\nfoi, acredite no que será"    
    },
    {
      "userId": 3,
      "id": 22,
      "title": "Imagem 22",
      "body": "A beleza está na perspectiva, nos\ndetalhes, no seu olhar, não nas coisas"    
    },
    {
      "userId": 3,
      "id": 23,
      "title": "Imagem 23",
      "body": "Me permito sorrir ao sol, entrego\nminha oração aos céus e aguardo "    
    },
    {
      "userId": 3,
      "id": 24,
      "title": "Imagem 24",
      "body": "Um passo de cada vez, com a\nfé transbordando no coração"    
    },
    {
      "userId": 3,
      "id": 25,
      "title": "Imagem 25",
      "body": "Eu sou bem mais que os seus olhos\npodem captar: sou imensidão"    
    },
    {
      "userId": 3,
      "id": 26,
      "title": "Imagem 26",
      "body": "Entenda que se não tivesse tanta\nintensidade, meu bem, não seria eu"    
    },
    {
      "userId": 3,
      "id": 27,
      "title": "Imagem 27",
      "body": "Quando a gente se aceita por inteiro,\naprendemos o que é o amor."    
    },
    {
      "userId": 3,
      "id": 28,
      "title": "Imagem 28",
      "body": "Esteja por inteira, independente\nde onde estiver"    
    },
    {
      "userId": 3,
      "id": 29,
      "title": "Imagem 29",
      "body": "Livre para sentir o que a vida quer causar,\nlivre para ir para qualquer lugar"    
    },
    {
      "userId": 3,
      "id": 30,
      "title": "Imagem 30",
      "body": "Sou brisa leve e só\no amor me guia"    
    },
    {
      "userId": 4,
      "id": 31,
      "title": "Imagem 31",
      "body": "Fé, a paz e o\nsorriso inabalável."    
    },
    {
      "userId": 4,
      "id": 32,
      "title": "Imagem 32",
      "body": "Ela tá com a fé, a paz\ne o sorriso inabalavel"    
    },
    {
      "userId": 4,
      "id": 33,
      "title": "Imagem 33",
      "body": "Essa calma na alma é de quem\naprendeu que tudo acontece no tempo certo"    
    },
    {
      "userId": 4,
      "id": 34,
      "title": "Imagem 34",
      "body": "Pode chegar, até se aconchegar,\nmas repare meu bem, amor aqui só\nvem somar, nunca faltou"    
    },
    {
      "userId": 4,
      "id": 35,
      "title": "Imagem 35",
      "body": "No pouco que faz,\npõe tudo que é"    
    },
    {
      "userId": 4,
      "id": 36,
      "title": "Imagem 36",
      "body": "Existir é ser casa de todos\nos sentimentos do mundo"    
    },
    {
      "userId": 4,
      "id": 37,
      "title": "Imagem 37",
      "body": "Seguindo um caminho tão meu que já não há\nmais tempo para viver nas expectativas alheias"    
    },
    {
      "userId": 4,
      "id": 38,
      "title": "Imagem 38",
      "body": "Aprender a fazer música\ncom o ritmo da vida"    
    },
    {
      "userId": 4,
      "id": 39,
      "title": "Imagem 39",
      "body": "Me pertencer,\njá me basta"    
    },
    {
      "userId": 4,
      "id": 40,
      "title": "Imagem 40",
      "body": "A beleza mora nos detalhes que só\no seu coração consegue sentir"    
    },
    {
      "userId": 5,
      "id": 41,
      "title": "Imagem 41",
      "body": "Pra ter vida, segue a luz,\nseja ela onde f(l)or"    
    },
    {
      "userId": 5,
      "id": 42,
      "title": "Imagem 42",
      "body": "me exploro, me descubro,\nme aceito, me celebro"    
    },
    {
      "userId": 5,
      "id": 43,
      "title": "Imagem 43",
      "body": "Você atrai exatamente o que o que é\ne o que te falta em igual proporção"    
    },
    {
      "userId": 5,
      "id": 44,
      "title": "Imagem 44",
      "body": "Ela é pura leveza,\né amante da vida"    
    },
    {
      "userId": 5,
      "id": 45,
      "title": "Imagem 45",
      "body": "Me exploro, me descubro,\nme aceito, me celebro"    
    },
    {
      "userId": 5,
      "id": 46,
      "title": "Imagem 46",
      "body": "Ser simples é o que\nte faz ser grande"    
    },
    {
      "userId": 5,
      "id": 47,
      "title": "Imagem 47",
      "body": "Coração em paz floresce\nmesmo sozinho"    
    },
    {
      "userId": 5,
      "id": 48,
      "title": "Imagem 48",
      "body": "Ela é mulher forte e resistente, que caminha\nde cabeça erguida. Ela é luz"    
    },
    {
      "userId": 5,
      "id": 49,
      "title": "Imagem 49",
      "body": "Apesar dos conflitos internos, ela segue\nsendo do bem, ela é toda coração"    
    },
    {
      "userId": 5,
      "id": 50,
      "title": "Imagem 50",
      "body": "Dona de várias formas de si mesma, mulher de\nopinião própria que segue com sabedoria."    
    },
    {
      "userId": 6,
      "id": 51,
      "title": "Imagem 51",
      "body": "Ela ama a sua calma interior e se\nrecusa a se deixar levar pela pressa"    
    },
    {
      "userId": 6,
      "id": 52,
      "title": "Imagem 52",
      "body": "Sua positividade pode ser surpreendente,\nela é feita de transformações,\ntem estilo e é iluminada por dentro"    
    },
    {
      "userId": 6,
      "id": 53,
      "title": "Imagem 53",
      "body": "Nasci pra viver a história mais\nimportante de todas - a minha."    
    },
    {
      "userId": 6,
      "id": 54,
      "title": "Imagem 54",
      "body": "Intensa por natureza,\nno riso e no amor"    
    },
    {
      "userId": 6,
      "id": 55,
      "title": "Imagem 55",
      "body": "A gente vai perdendo algumas coisas pelo\ncaminho, mas jamais deve se perder de si mesmo"    
    },
    {
      "userId": 6,
      "id": 56,
      "title": "Imagem 56",
      "body": "Ela tem uma alma de passarinho, não\nnasceu para ficar presa nem em si mesma."    
    },
    {
      "userId": 6,
      "id": 57,
      "title": "Imagem 57",
      "body": "Apenas assim: livre, leve e carregando\nos melhores pensamentos. Pro dia e pra vida."    
    },
    {
      "userId": 6,
      "id": 58,
      "title": "Imagem 58",
      "body": "Sorriso doce que faz apaixonar…"    
    },
    {
      "userId": 6,
      "id": 59,
      "title": "Imagem 59",
      "body": "O que você faz na sua vida é um retrato\nperfeito do que cultiva em seu coração."    
    },
    {
      "userId": 6,
      "id": 60,
      "title": "Imagem 60",
      "body": "Que a vida passe sem pressa, que tenha amor\nem cada dia e que Deus abençoe cada escolha\nque meu coração fizer por mim. "    
    },
    {
      "userId": 7,
      "id": 61,
      "title": "Imagem 61",
      "body": "Que a gente consiga entender que a\nmaior sorte da vida está em agradecer! "    
    },
    {
      "userId": 7,
      "id": 62,
      "title": "Imagem 62",
      "body": "Sorriso aberto, alma livre!"    
    },
    {
      "userId": 7,
      "id": 63,
      "title": "Imagem 63",
      "body": "Plantei o amor em mim, para\nque eu pudesse florescer."    
    },
    {
      "userId": 7,
      "id": 64,
      "title": "Imagem 64",
      "body": "Na bondade dos seus gestos transparece\na paz que vive no seu coração"    
    },
    {
      "userId": 7,
      "id": 65,
      "title": "Imagem 65",
      "body": "Pouco importa a estação, pelos\nolhos dela é sempre primavera."    
    },
    {
      "userId": 7,
      "id": 66,
      "title": "Imagem 66",
      "body": "Administra bem suas finanças,\nnão deve perfeição a ninguém"    
    },
    {
      "userId": 7,
      "id": 67,
      "title": "Imagem 67",
      "body": "Ciclos são finalizados, novos começos dão as\ncaras. A vida muda e eu escolho mudar com ela."    
    },
    {
      "userId": 7,
      "id": 68,
      "title": "Imagem 68",
      "body": "A felicidade está em você,\ndeixe transbordar."    
    },
    {
      "userId": 7,
      "id": 69,
      "title": "Imagem 69",
      "body": "A gente ganha asas quando não\ntem medo de voar."    
    },
    {
      "userId": 7,
      "id": 70,
      "title": "Imagem 70",
      "body": "Cada momento de vida é\num momento de gratidão"    
    },
    {
      "userId": 8,
      "id": 71,
      "title": "Imagem 71",
      "body": "Convicção dos meus valores, felicidade\nnas minhas escolhas"    
    },
    {
      "userId": 8,
      "id": 72,
      "title": "Imagem 72",
      "body": "Ser intensa é a minha essência."    
    },
    {
      "userId": 8,
      "id": 73,
      "title": "Imagem 73",
      "body": "Só veem as belezas do mundo, aqueles\nque têm belezas dentro de si."    
    },
    {
      "userId": 8,
      "id": 74,
      "title": "Imagem 74",
      "body": "Bonito mesmo, é quando a beleza do\ncoração transparece no rosto."    
    },
    {
      "userId": 8,
      "id": 75,
      "title": "Imagem 75",
      "body": "As coisas que amamos dizem\nmuito sobre quem somos!"    
    },
    {
      "userId": 8,
      "id": 76,
      "title": "Imagem 76",
      "body": "Ela se antecipou! Foi ser\nfeliz antes do final."    
    },
    {
      "userId": 8,
      "id": 77,
      "title": "Imagem 77",
      "body": "Fale coisas boas, suas palavras tem poder!"    
    },
    {
      "userId": 8,
      "id": 78,
      "title": "Imagem 78",
      "body": "Intensa por natureza, no riso e no amor."    
    },
    {
      "userId": 8,
      "id": 79,
      "title": "Imagem 79",
      "body": "Se entregue ao ritmo da vida e flua com ele!"    
    },
    {
      "userId": 8,
      "id": 80,
      "title": "Imagem 80",
      "body": "Os exageros moram em sua pele, as\nintensidades estão na sua essência."    
    },
    {
      "userId": 9,
      "id": 81,
      "title": "Imagem 81",
      "body": "Ela é bem mais que uma flor.\nÉ coragem vestida de pétalas"    
    },
    {
      "userId": 9,
      "id": 82,
      "title": "Imagem 82",
      "body": "De luz em luz, eu me tornei meu próprio sol."    
    },
    {
      "userId": 9,
      "id": 83,
      "title": "Imagem 83",
      "body": "Escolha ela acima de tudo."    
    },
    {
      "userId": 9,
      "id": 84,
      "title": "Imagem 84",
      "body": "Atirada, confiante, inteira"    
    },
    {
      "userId": 9,
      "id": 85,
      "title": "Imagem 85",
      "body": "Ser feliz é um ato de amor: por si,\npor tudo que foi, pelo que ficou."    
    },
    {
      "userId": 9,
      "id": 86,
      "title": "Imagem 86",
      "body": "Você é primavera em todos\nos seus tons, floresça."    
    },
    {
      "userId": 9,
      "id": 87,
      "title": "Imagem 87",
      "body": "Aprendeu sozinha que ser mulher é\nter uma força que vem da alma!"    
    },
    {
      "userId": 9,
      "id": 88,
      "title": "Imagem 88",
      "body": "Ela mergulhou fundo, dentro de si,\ne encontrou tudo que buscava: a sua\nprópria verdade, a sua essência."    
    },
    {
      "userId": 9,
      "id": 89,
      "title": "Imagem 89",
      "body": "Coloque o seu coração em tudo o que fizer\ne todos os seus planos darão certo."    
    },
    {
      "userId": 9,
      "id": 90,
      "title": "Imagem 90",
      "body": "Ela é poesia pra ser lida com a alma."    
    },
    {
      "userId": 10,
      "id": 91,
      "title": "Imagem 91",
      "body": "Daquelas que já acorda com vontade de vencer, e\né por isso que nunca desiste do que quer."    
    },
    {
      "userId": 10,
      "id": 92,
      "title": "Imagem 92",
      "body": "Erguendo-me no corpo de uma mulher que nunca\ndeixou de confiar na alma de menina."    
    },
    {
      "userId": 10,
      "id": 93,
      "title": "Imagem 93",
      "body": "Daquelas que já acorda com vontade de vencer, e\né por isso que nunca desiste do que quer."    
    },
    {
      "userId": 10,
      "id": 94,
      "title": "Imagem 94",
      "body": "Erguendo-me no corpo de uma mulher que nunca\ndeixou de confiar na alma de menina."    
    },
    {
      "userId": 10,
      "id": 95,
      "title": "Imagem 95",
      "body": "Se amar para florescer. "    
    },
    {
      "userId": 10,
      "id": 96,
      "title": "Imagem 96",
      "body": "Decore sua alma com sorrisos sinceros."    
    },
    {
      "userId": 10,
      "id": 97,
      "title": "Imagem 97",
      "body": "O charmoso costume de sorrir\npra vida, eu não perco jamais"    
    },
    {
      "userId": 10,
      "id": 98,
      "title": "Imagem 98",
      "body": "De alma leve e de mente livre,\no coração só pulsa amor."    
    },
    {
      "userId": 10,
      "id": 99,
      "title": "Imagem 99",
      "body": "Que a gente não perca essa ousadia de\ntentar ser feliz todos os dias"    
    },
    {
      "userId": 10,
      "id": 100,
      "title": "Imagem 100",
      "body": "O primeiro dos bens, depois da\nsaúde, é a paz interior. "    
    }
  ]